djaws/__init__.py
djaws/apps.py
djaws/cloudformation/__init__.py
djaws/cloudformation/exceptions.py
djaws/cloudformation_api.py
djaws/cognito/__init__.py
djaws/cognito/exceptions.py
djaws/cognito_api.py
djaws/decorators.py
djaws/exceptions.py
djaws/management/__init__.py
djaws/management/commands/__init__.py
djaws/management/commands/create_public_s3_bucket.py
djaws/management/commands/describe_stacks.py
djaws/s3/__init__.py
djaws/s3/exceptions.py
djaws/s3_api.py
djaws/tests/__init__.py
djaws/tests/schemas/__init__.py
djaws/tests/schemas/cloudformation/__init__.py
djaws/tests/schemas/cloudformation/describe_stacks.json
djaws/tests/schemas/cognito/__init__.py
djaws/tests/schemas/cognito/admin_confirm_sign_up.json
djaws/tests/schemas/cognito/initiate_auth.json
djaws/tests/schemas/cognito/signup_new_user.json
djaws/tests/schemas/s3/__init__.py
djaws/tests/schemas/s3/create_bucket.json
djaws/tests/schemas/s3/generate_presigned_post.json
djaws/tests/test_cloudformation_api.py
djaws/tests/test_cognito_api.py
djaws/tests/test_decorators.py
djaws/tests/test_s3_api.py
djaws/utils.py
dj_aws-0.1.5.dist-info/WHEEL
dj_aws-0.1.5.dist-info/METADATA
dj_aws-0.1.5.dist-info/RECORD
