Metadata-Version: 2.1
Name: dj-aws
Version: 0.1.5
Summary: Django + AWS made easy
Home-page: https://github.com/adrianmeraz/dj-aws
Author: Adrian
Author-email: adrian@rydeas.com
Requires-Python: >=3.9,<4.0
Classifier: Programming Language :: Python :: 3
Classifier: Programming Language :: Python :: 3.9
Classifier: Programming Language :: Python :: 3.10
Requires-Dist: Django (>=3.2.15,<3.3.0)
Requires-Dist: PyJWT[crypto] (>=2.3.0,<3.0.0)
Requires-Dist: boto3 (>=1.24.77,<1.25.0)
Requires-Dist: dj-starter (>=0.1.12,<0.2.0)
Project-URL: Repository, https://github.com/adrianmeraz/dj-aws
